jadwal_shalat/__init__.py
jadwal_shalat/config.py
jadwal_shalat/jadwal.py
jadwal_shalat-0.0.2.dist-info/LICENSE
jadwal_shalat-0.0.2.dist-info/METADATA
jadwal_shalat-0.0.2.dist-info/WHEEL
jadwal_shalat-0.0.2.dist-info/entry_points.txt
jadwal_shalat-0.0.2.dist-info/top_level.txt
jadwal_shalat-0.0.2.dist-info/RECORD
