Metadata-Version: 2.1
Name: jadwal-shalat
Version: 0.0.2
Summary: Simple Jadwal Shalat
Home-page: https://gitlab.com/nesstero/jadwal-shalat
Author: nestero
Author-email: nestero@mail.com
License: MIT
License-File: LICENSE
